[
  {
    "id": 1,
    "target_vip": "Virat Kohli",
    "platform": "Instagram",
    "post_caption": "Breaking: Virat Kohli announces retirement from international cricket! 😢 #ViratKohli #Cricket",
    "media_url": "https://images.unsplash.com/photo-1551698618-1dfe5d97d256?w=400&h=400&fit=crop",
    "fake_account": "@fake_virat_kohli_official",
    "likes": 12500,
    "comments": 890,
    "shares": 2100,
    "risk_level": "High",
    "reason": "Fake retirement announcement with high engagement",
    "detected_at": "2024-01-15T10:30:00Z",
    "url": "https://instagram.com/p/fake_post_1"
  },
  {
    "id": 2,
    "target_vip": "Priyanka Chopra",
    "platform": "Instagram",
    "post_caption": "Exclusive: Priyanka Chopra reveals she's pregnant with twins! 👶👶 #PriyankaChopra #Pregnancy",
    "media_url": "https://images.unsplash.com/photo-1555252333-9f8e92e65df9?w=400&h=400&fit=crop",
    "fake_account": "@priyanka_chopra_fan",
    "likes": 8900,
    "comments": 1200,
    "shares": 1800,
    "risk_level": "Medium",
    "reason": "False pregnancy announcement",
    "detected_at": "2024-01-15T09:15:00Z",
    "url": "https://instagram.com/p/fake_post_2"
  },
  {
    "id": 3,
    "target_vip": "Elon Musk",
    "platform": "Instagram",
    "post_caption": "Tesla stock will hit $1000 tomorrow! Buy now! 🚀💰 #Tesla #StockMarket #ElonMusk",
    "media_url": "https://images.unsplash.com/photo-1611974789855-9c2a0a7236a3?w=400&h=400&fit=crop",
    "fake_account": "@elon_musk_official_fake",
    "likes": 15600,
    "comments": 2100,
    "shares": 3200,
    "risk_level": "High",
    "reason": "Financial misinformation and stock manipulation",
    "detected_at": "2024-01-15T08:45:00Z",
    "url": "https://instagram.com/p/fake_post_3"
  },
  {
    "id": 4,
    "target_vip": "Deepika Padukone",
    "platform": "Instagram",
    "post_caption": "Deepika Padukone endorses this weight loss product! Lost 20kg in 30 days! 💊 #WeightLoss #DeepikaPadukone",
    "media_url": "https://images.unsplash.com/photo-1559757148-5c350d0d3c56?w=400&h=400&fit=crop",
    "fake_account": "@deepika_weight_loss",
    "likes": 6700,
    "comments": 950,
    "shares": 1400,
    "risk_level": "Medium",
    "reason": "Fake product endorsement",
    "detected_at": "2024-01-15T07:20:00Z",
    "url": "https://instagram.com/p/fake_post_4"
  },
  {
    "id": 5,
    "target_vip": "Narendra Modi",
    "platform": "Instagram",
    "post_caption": "PM Modi announces free electricity for all Indians! ⚡🇮🇳 #FreeElectricity #Modi #India",
    "media_url": "https://images.unsplash.com/photo-1466611653911-95081537e5b7?w=400&h=400&fit=crop",
    "fake_account": "@modi_official_fake",
    "likes": 18900,
    "comments": 3200,
    "shares": 4500,
    "risk_level": "High",
    "reason": "Political misinformation with high viral potential",
    "detected_at": "2024-01-15T06:30:00Z",
    "url": "https://instagram.com/p/fake_post_5"
  }
]
